desc/__init__.py
desc/datasets/__init__.py
desc/datasets/pbmc.h5ad
desc/datasets/pbmc_processed.h5ad
desc/models/SAE.py
desc/models/__init__.py
desc/models/desc.py
desc/models/network.py
desc/tools/__init__.py
desc/tools/downstream.py
desc/tools/preprocessing.py
desc/tools/read.py
desc/tools/test.py
desc/tools/write.py
desc-2.1.1.dist-info/METADATA
desc-2.1.1.dist-info/WHEEL
desc-2.1.1.dist-info/top_level.txt
desc-2.1.1.dist-info/RECORD
