Metadata-Version: 2.1
Name: desc
Version: 2.1.1
Summary: Deep Embedded Single-cell RNA-seq Clustering
Home-page: https://github.com/eleozzr/desc
Author: Xiangjie Li, Gang Hu, Mingyao Li, Yafei Lyu
Author-email: ele717@163.com, huggs@nankai.edu.cn, mingyao@pennmedicine.upenn.edu, lyuyafei@gmail.com
License: MIT
Platform: UNKNOWN
Classifier: Development Status :: 3 - Alpha
Classifier: Programming Language :: Python :: 3.5
Classifier: Programming Language :: Python :: 3.6
Requires-Dist: matplotlib (>=2.2pydot)
Requires-Dist: tensorflow
Requires-Dist: scanpy
Requires-Dist: louvain
Requires-Dist: python-igraph
Requires-Dist: h5py
Requires-Dist: pandas
